{
  "parent": "nestle:nestle_advancement",
  "criteria": {
    "nestle_require": {
      "conditions": {
        "require": {
          "distance": 0,
          "seconds": 1
        }
      },
      "trigger": "nestle:nestle_value_require"
    }
  },
  "display": {
    "description": {
      "translate": "advancements.nestle.nestle_close_advancement.description"
    },
    "icon": {
      "count": 1,
      "id": "minecraft:cobweb"
    },
    "title": {
      "translate": "advancements.nestle.nestle_close_advancement.title"
    }
  },
  "requirements": [
    [
      "nestle_require"
    ]
  ],
  "sends_telemetry_event": true
}